protocols_dispatcher/__init__.py
protocols_dispatcher/dispatcher.py
protocols_dispatcher/py.typed
protocols_dispatcher/transports/__init__.py
protocols_dispatcher/transports/serial.py
protocols_dispatcher-0.2.0.dist-info/METADATA
protocols_dispatcher-0.2.0.dist-info/WHEEL
protocols_dispatcher-0.2.0.dist-info/licenses/LICENSE
protocols_dispatcher-0.2.0.dist-info/RECORD
