Metadata-Version: 2.4
Name: protocols-dispatcher
Version: 0.2.0
Summary: Гибкая асинхронная библиотека для диспетчеризации бинарных протоколов
Project-URL: PyPI, https://pypi.org/project/protocols_dispatcher/
Project-URL: Homepage, https://github.com/Enigma0960/protocols_dispatcher
Project-URL: Source, https://github.com/Enigma0960/protocols_dispatcher
Project-URL: Issues, https://github.com/Enigma0960/protocols_dispatcher/issues
Author-email: Supryadkin Igor <igorsupr@gamail.com>
License: MIT License
License-File: LICENSE
Classifier: Intended Audience :: Developers
Classifier: License :: OSI Approved :: MIT License
Classifier: Programming Language :: Python :: 3 :: Only
Requires-Python: >=3.9
Requires-Dist: typing-extensions; python_version < '3.11'
Provides-Extra: all
Requires-Dist: aioserial; extra == 'all'
Requires-Dist: pytest-asyncio>=1.0.0; (python_version >= '3.8') and extra == 'all'
Requires-Dist: pytest-cov>=6.2.1; extra == 'all'
Requires-Dist: pytest-mock>=3.14.1; extra == 'all'
Requires-Dist: pytest>=8.4.1; extra == 'all'
Provides-Extra: dev
Requires-Dist: pytest-asyncio>=1.0.0; (python_version >= '3.8') and extra == 'dev'
Requires-Dist: pytest-cov>=6.2.1; extra == 'dev'
Requires-Dist: pytest-mock>=3.14.1; extra == 'dev'
Requires-Dist: pytest>=8.4.1; extra == 'dev'
Provides-Extra: serial
Requires-Dist: aioserial; extra == 'serial'
